LinghundeZhenxiang/Dockerfile
LinghundeZhenxiang/README.md
LinghundeZhenxiang/__init__.py
LinghundeZhenxiang/__main__.py
LinghundeZhenxiang/file.epub
LinghundeZhenxiang/index.html
LinghundeZhenxiang/css/__init__.py
LinghundeZhenxiang/css/annotations.css
LinghundeZhenxiang/css/main.css
LinghundeZhenxiang/css/normalize.css
LinghundeZhenxiang/css/popup.css
LinghundeZhenxiang/font/__init__.py
LinghundeZhenxiang/font/fontello.eot
LinghundeZhenxiang/font/fontello.svg
LinghundeZhenxiang/font/fontello.ttf
LinghundeZhenxiang/font/fontello.woff
LinghundeZhenxiang/img/__init__.py
LinghundeZhenxiang/img/annotator-glyph-sprite.png
LinghundeZhenxiang/img/annotator-icon-sprite.png
LinghundeZhenxiang/img/apple-touch-icon.png
LinghundeZhenxiang/img/cancelfullscreen.png
LinghundeZhenxiang/img/close.png
LinghundeZhenxiang/img/fullscreen.png
LinghundeZhenxiang/img/loader.gif
LinghundeZhenxiang/img/menu-icon.png
LinghundeZhenxiang/img/save.png
LinghundeZhenxiang/img/saved.png
LinghundeZhenxiang/img/settings-s.png
LinghundeZhenxiang/img/settings.png
LinghundeZhenxiang/img/star.png
LinghundeZhenxiang/js/__init__.py
LinghundeZhenxiang/js/epub.js
LinghundeZhenxiang/js/epub.min.js
LinghundeZhenxiang/js/epub.min.map
LinghundeZhenxiang/js/hooks.min.js
LinghundeZhenxiang/js/hooks.min.map
LinghundeZhenxiang/js/reader.js
LinghundeZhenxiang/js/reader.js.map
LinghundeZhenxiang/js/reader.min.js
LinghundeZhenxiang/js/reader.min.map
LinghundeZhenxiang/js/hooks/__init__.py
LinghundeZhenxiang/js/hooks/extensions/__init__.py
LinghundeZhenxiang/js/hooks/extensions/highlight.js
LinghundeZhenxiang/js/libs/__init__.py
LinghundeZhenxiang/js/libs/jquery.min.js
LinghundeZhenxiang/js/libs/localforage.min.js
LinghundeZhenxiang/js/libs/screenfull.js
LinghundeZhenxiang/js/libs/screenfull.min.js
LinghundeZhenxiang/js/libs/zip.min.js
LinghundeZhenxiang/js/plugins/__init__.py
LinghundeZhenxiang/js/plugins/hypothesis.js
LinghundeZhenxiang/js/plugins/search.js
linghunde_zhenxiang-2022.10.3.0.dist-info/METADATA
linghunde_zhenxiang-2022.10.3.0.dist-info/WHEEL
linghunde_zhenxiang-2022.10.3.0.dist-info/entry_points.txt
linghunde_zhenxiang-2022.10.3.0.dist-info/top_level.txt
linghunde_zhenxiang-2022.10.3.0.dist-info/RECORD
